{"cameraMode":{"drawMode":0,"name":"Shaded","section":"Shading Mode"},"sceneLighting":true,"audioPlay":false,"sceneViewState":{"showFog":true,"showMaterialUpdate":false,"showSkybox":true,"showFlares":true,"showImageEffects":true,"showParticleSystems":true},"in2DMode":false,"pivot":{"x":-6.437251091003418,"y":3.3289613723754885,"z":-0.7385096549987793},"rotation":{"x":-0.008655006065964699,"y":0.990432620048523,"z":-0.07323341816663742,"w":-0.11674180626869202},"size":1.478428840637207,"orthographic":false}